{
  "kind": "collectionType",
  "collectionName": "services",
  "info": {
    "singularName": "service",
    "pluralName": "services",
    "displayName": "service",
    "description": ""
  },
  "options": {
    "draftAndPublish": true
  },
  "pluginOptions": {
    "i18n": {
      "localized": true
    }
  },
  "attributes": {
    "title": {
      "pluginOptions": {
        "i18n": {
          "localized": true
        }
      },
      "type": "string",
      "required": true
    },
    "description": {
      "pluginOptions": {
        "i18n": {
          "localized": true
        }
      },
      "type": "text",
      "required": true
    },
    "price": {
      "pluginOptions": {
        "i18n": {
          "localized": false
        }
      },
      "type": "integer",
      "required": true,
      "min": 0
    },
    "period": {
      "pluginOptions": {
        "i18n": {
          "localized": true
        }
      },
      "type": "string",
      "required": true
    },
    "ruLocaleId": {
      "pluginOptions": {
        "i18n": {
          "localized": true
        }
      },
      "type": "string"
    }
  }
}
